Metadata-Version: 1.2
Name: xvfbman
Version: 1.0.0
Summary: A python module for managing Xvfb sessions / ensuring DISPLAY through a simple interface
Home-page: https://github.com/kata198/xvfbman
Author: Tim Savannah
Author-email: kata198@gmail.com
Maintainer: Tim Savannah
Maintainer-email: kata198@gmail.com
License: LGPLv2
Keywords: python,Xvfb,manage,xvfbman,DISPLAY,X11,screen,Xorg,virtual,framebuffer
Platform: UNKNOWN
Classifier: Development Status :: 5 - Production/Stable
Classifier: Programming Language :: Python
Classifier: License :: OSI Approved :: GNU Lesser General Public License v2 (LGPLv2)
Classifier: Programming Language :: Python :: 2
Classifier: Programming Language :: Python :: 2
Classifier: Programming Language :: Python :: 2.7
Classifier: Programming Language :: Python :: 3
Classifier: Programming Language :: Python :: 3.3
Classifier: Programming Language :: Python :: 3.4
Classifier: Programming Language :: Python :: 3.5
Classifier: Programming Language :: Python :: 3.6
Classifier: Programming Language :: Python :: 3.7
Classifier: Environment :: X11 Applications
Classifier: Operating System :: POSIX
Classifier: Topic :: Multimedia :: Graphics
Classifier: Topic :: Software Development :: Libraries :: Python Modules
Classifier: Topic :: Software Development :: Testing
